{"openapi":"3.0.1","info":{"title":"OpenAPI definition","version":"v0"},"servers":[{"url":"http://localhost:8000","description":"Generated server url"}],"paths":{"/api/tickets/{id}":{"put":{"tags":["flight-ticket-controller"],"operationId":"updateTicket","parameters":[{"name":"id","in":"path","required":true,"schema":{"type":"integer","format":"int64"}}],"requestBody":{"content":{"application/json":{"schema":{"$ref":"#/components/schemas/FlightTicket"}}},"required":true},"responses":{"200":{"description":"OK","content":{"*/*":{"schema":{"type":"object"}}}}}},"delete":{"tags":["flight-ticket-controller"],"operationId":"deleteTicket","parameters":[{"name":"id","in":"path","required":true,"schema":{"type":"integer","format":"int64"}}],"responses":{"200":{"description":"OK","content":{"*/*":{"schema":{"type":"object"}}}}}}},"/api/tickets":{"get":{"tags":["flight-ticket-controller"],"operationId":"getTickets","responses":{"200":{"description":"OK","content":{"*/*":{"schema":{"type":"array","items":{"$ref":"#/components/schemas/FlightTicket"}}}}}}},"post":{"tags":["flight-ticket-controller"],"operationId":"bookTicket","requestBody":{"content":{"application/json":{"schema":{"$ref":"#/components/schemas/FlightTicket"}}},"required":true},"responses":{"200":{"description":"OK","content":{"*/*":{"schema":{"type":"object"}}}}}}},"/api/user/profile":{"get":{"tags":["user-controller"],"operationId":"user","responses":{"200":{"description":"OK","content":{"*/*":{"schema":{"type":"object","properties":{"name":{"type":"string"}}}}}}}}},"/api/tickets/kickoff/{kickoff}":{"get":{"tags":["flight-ticket-controller"],"operationId":"byKickoff","parameters":[{"name":"kickoff","in":"path","required":true,"schema":{"type":"string"}}],"responses":{"200":{"description":"OK","content":{"*/*":{"schema":{"type":"array","items":{"$ref":"#/components/schemas/FlightTicket"}}}}}}}},"/api/tickets/health":{"get":{"tags":["flight-ticket-controller"],"operationId":"health","responses":{"200":{"description":"OK","content":{"*/*":{"schema":{"type":"string"}}}}}}},"/api/tickets/destination/{dest}":{"get":{"tags":["flight-ticket-controller"],"operationId":"byDestination","parameters":[{"name":"dest","in":"path","required":true,"schema":{"type":"string"}}],"responses":{"200":{"description":"OK","content":{"*/*":{"schema":{"type":"array","items":{"$ref":"#/components/schemas/FlightTicket"}}}}}}}},"/api/tickets/date/{date}":{"get":{"tags":["flight-ticket-controller"],"operationId":"byDate","parameters":[{"name":"date","in":"path","required":true,"schema":{"type":"string"}}],"responses":{"200":{"description":"OK","content":{"*/*":{"schema":{"type":"array","items":{"$ref":"#/components/schemas/FlightTicket"}}}}}}}}},"components":{"schemas":{"FlightTicket":{"required":["destinationAddress","kickoffAddress","passengerName"],"type":"object","properties":{"id":{"type":"integer","description":"Unique identifier for the ticket","format":"int64","example":1},"passengerName":{"maxLength":2147483647,"minLength":3,"type":"string","description":"Name of the passenger","example":"John Doe"},"kickoffAddress":{"maxLength":2147483647,"minLength":2,"type":"string","description":"Departure location","example":"Berlin"},"destinationAddress":{"maxLength":2147483647,"minLength":2,"type":"string","description":"Destination location","example":"Paris"},"bookingDate":{"type":"string","description":"Date of booking","format":"date","example":"2024-06-20"},"createdAt":{"type":"string","description":"Timestamp when the ticket was created","format":"date-time"},"userId":{"type":"string","description":"ID of the user who owns this ticket","example":"46952d32-b6ab-411e-8530-316b209d75a3"}},"description":"A flight ticket entity"}}}}